BeautifulFinance/data_processing.py
BeautifulFinance/explore.py
BeautifulFinance/model.py
BeautifulFinance/visualization.py
BeautifulFinance-0.1.dist-info/LICENSE.txt
BeautifulFinance-0.1.dist-info/METADATA
BeautifulFinance-0.1.dist-info/WHEEL
BeautifulFinance-0.1.dist-info/top_level.txt
BeautifulFinance-0.1.dist-info/RECORD
