Metadata-Version: 2.1
Name: BeautifulFinance
Version: 0.1
Summary: A wrapper API of finance
Home-page: https://github.com/Amethyst1016/DATA534_Project
Author: Amethyst He
Author-email: hejinghongyue@outlook.com
License: MIT
License-File: LICENSE.txt
